setup.py
dev-examples/__init__.py
dev-examples/py_tvl1.py
dev-examples/tvl1.py
dev-examples/optical_flow/__init__.py
dev-examples/optical_flow/hs_cg.py
dev-examples/optical_flow/hs_cg_numpy.py
dev-examples/optical_flow/hs_jacobi.py
dev-examples/optical_flow/hs_jacobi_multi.py
dev-examples/optical_flow/hs_jacobi_numpy.py
dev-examples/optical_flow/hs_jacobi_single.py
dev-examples/optical_flow/hs_jacobi_webcam.py
dev-examples/optical_flow/ik.py
dev-examples/optical_flow/png_to_raw.py
dev-examples/optical_flow/r5demo_capture.py
dev-examples/optical_flow/r5demo_webcam.py
dev-examples/optical_flow/sequence.py
dev-examples/optical_flow/show_raw_images.py
dev-examples/optical_flow/solver.py
dev-examples/optical_flow/tvl1.py
dev-examples/optical_flow/webcam.py
dev-examples/optical_flow/riscv-demo/__init__.py
dev-examples/optical_flow/riscv-demo/create_moving_bar.py
dev-examples/optical_flow/riscv-demo/webcam_file.py
examples-copy/__init__.py
examples-copy/optical_flow/__init__.py
examples-copy/optical_flow/hs_jacobi.py
examples-copy/optical_flow/hs_jacobi_multi.py
examples-copy/optical_flow/hs_jacobi_numpy.py
examples-copy/optical_flow/hs_jacobi_single.py
examples-copy/optical_flow/hs_jacobi_webcam.py
examples-copy/optical_flow/ik.py
examples-copy/optical_flow/png_to_raw.py
examples-copy/optical_flow/r5demo_capture.py
examples-copy/optical_flow/r5demo_webcam.py
examples-copy/optical_flow/sequence.py
examples-copy/optical_flow/show_raw_images.py
examples-copy/optical_flow/solver.py
examples-copy/optical_flow/tvl1.py
examples-copy/optical_flow/webcam.py
examples-copy/optical_flow/riscv-demo/__init__.py
examples-copy/optical_flow/riscv-demo/create_moving_bar.py
examples-copy/optical_flow/riscv-demo/webcam_file.py
examples-riscv/__init__.py
examples-riscv/tvl1.py
examples-riscv/optical_flow/__init__.py
examples-riscv/optical_flow/hs_jacobi.py
examples-riscv/optical_flow/hs_jacobi_c.py
examples-riscv/optical_flow/hs_jacobi_multi.py
examples-riscv/optical_flow/hs_jacobi_numpy.py
hindemith.egg-info/PKG-INFO
hindemith.egg-info/SOURCES.txt
hindemith.egg-info/dependency_links.txt
hindemith.egg-info/pbr.json
hindemith.egg-info/requires.txt
hindemith.egg-info/top_level.txt
