Metadata-Version: 1.0
Name: hindemith
Version: 0.1.1
Summary: Package containing a suite of high performance pattern specializers
Home-page: https://github.com/ucb-sejits/hindemith
Author: Leonard Truong
Author-email: leonardtruong@berkeley.edu
License: UNKNOWN
Platform: UNKNOWN
